{
  "search": [
    "battle stages in Street Fighter VI"
  ],
  "result": {
    "battle stages in Street Fighter VI": [
      {
        "page": 1,
        "results": [
          {
            "snippet": "Finally, the best stage in Street Fighter 6 is undoubtedly Tian Hong Yuan, based on the breathtaking Yu Garden in China. This was the best stage in the beta ...",
            "title": "Every Stage In Street Fighter 6, Ranked",
            "url": "https://www.thegamer.com/street-fighter-6-sfvi-all-arenas-best-ranked/"
          },
          {
            "snippet": "My favorite is Cammy's stage. Also (Akuma's) temple from SFV. Sagat's open field in a thunder storm.",
            "title": "Stages for Street Fighter VI : r/StreetFighter",
            "url": "https://www.reddit.com/r/StreetFighter/comments/v7lqjc/stages_for_street_fighter_vi/"
          },
          {
            "snippet": "Visit Battle Settings to adjust settings pertaining to online matches. Matchmaking Turn on matchmaking for ranked or casual matches and search for an opponent.",
            "title": "Battle Settings | STREET FIGHTER 6 Official Web Manual",
            "url": "https://game.capcom.com/manual/SF6/en/ps5/page/6/7"
          },
          {
            "snippet": "Introducing the Fighters Edition! Including all characters and stages from both Year 1 and 2, it's perfect for those new to the game!",
            "title": "Street Fighter 6 Years 1-2 Fighters Edition｜CAPCOM",
            "url": "https://www.streetfighter.com/6/contents/y12-fe/"
          },
          {
            "snippet": "Listed here are the various stages in the Street Fighter series. Trending pages. Ayutthaya Ruins. Pao Pao Cafe. Temple Hideout. Air Force Base. Bonus Stage.",
            "title": "Category:Stages - Street Fighter Wiki - Fandom",
            "url": "https://streetfighter.fandom.com/wiki/Category:Stages"
          },
          {
            "snippet": "All 16 Stages In Street Fighter 6, Ranked Worst To Best · 16 Training Room · 15 Carrier Byron Taylor · 14 The Macho Ring · 13 Thunderfoot Settlement.",
            "title": "All 16 Stages In Street Fighter 6, Ranked Worst To Best",
            "url": "https://screenrant.com/street-fighter-6-stages-ranked-worst-best/"
          },
          {
            "snippet": "",
            "title": "26 characters. 20 stages. Press start and fight your way to the ...",
            "url": "https://www.facebook.com/NintendoAmerica/videos/26-characters-20-stages-press-start-and-fight-your-way-to-the-top-street-fighter/1048136217415458/"
          },
          {
            "snippet": "World Tour mode acts as the story portion of Street Fighter 6 and it's how you upgrade the avatar you bring into the Battle Hub.",
            "title": "How the World Tour Mode works in Street Fighter 6",
            "url": "https://www.redbull.com/int-en/world-tour-mode-street-fighter-6"
          }
        ]
      }
    ]
  },
  "click": [
    {
      "from": "<search>battle stages in Street Fighter VI</search>",
      "to": "https://www.thegamer.com/street-fighter-6-sfvi-all-arenas-best-ranked/"
    }
  ]
}
