{
  "search": [
    "the Grammy Award for “Best New Artist” from 1995 through 2025",
    "sam smith gender"
  ],
  "result": {
    "the Grammy Award for “Best New Artist” from 1995 through 2025": [
      {
        "page": 1,
        "results": [
          {
            "snippet": "Sheryl Crow won in 1995. Hootie and the Blowfish won in ... The Grammy Award for Best New Artist was not presented during the 9th Grammy Awards.Read more",
            "title": "Grammy Award for Best New Artist",
            "url": "https://en.wikipedia.org/wiki/Grammy_Award_for_Best_New_Artist"
          },
          {
            "snippet": "She was also the first country artist to win the Best New Artist Grammy. ... In 2009, Adele won Best New Artist, and she earned the three other awards in ...Read more",
            "title": "Grammy Award milestones",
            "url": "https://en.wikipedia.org/wiki/Grammy_Award_milestones"
          },
          {
            "snippet": "From Bobby Darin to Olivia Rodrigo, Best New Artist Grammy winners through the years – photo gallery.",
            "title": "Grammy Best New Artist Winners Through The Years",
            "url": "https://deadline.com/gallery/grammy-best-new-artist-winners-list-photos/"
          },
          {
            "snippet": "Click through our photo gallery of all the Grammy winners for Best New Artist, from Alessia Cara, Chance the Rapper and Adele to The ...",
            "title": "Grammy Best New Artist: All the Winners in ...",
            "url": "https://www.goldderby.com/gallery/grammy-best-new-artist-all-the-winners/"
          },
          {
            "snippet": "Grammy Award for best new artist ; 1950s to 1970s. 1959: Bobby Darin. 1960: no ceremony was held ; 1980s and 1990s. 1980: Rickie Lee Jones ; 2000s and 2010s. 2000: ...Read more",
            "title": "Grammy Award for best new artist | Year, Winners, & Facts",
            "url": "https://www.britannica.com/topic/Grammy-Award-for-best-new-artist"
          },
          {
            "snippet": "Grammys best new artist winners through the years: Full list ahead of 2025 awards ... Sheryl Crow (37th Grammy Awards in 1995); Hootie & the ...Read more",
            "title": "Grammy Awards best new artist winners from 1959 to 2024",
            "url": "https://www.usatoday.com/story/entertainment/music/2025/01/20/grammy-awards-best-new-artist-winners-full-list/77549414007/"
          },
          {
            "snippet": "10 Grammy Best New Artist Winners & Losers ; 1995: Sheryl Crow Runners up: Ace of Base, Counting Crows, Crash Test Dummies, Green Day ; 1987: Bruce Hornsby and ...Read more",
            "title": "10 Grammy Best New Artist Winners & Losers",
            "url": "https://bestclassicbands.com/grammy-best-new-artist-winners-12-9-1555/"
          },
          {
            "snippet": "... award is presented to the songwriter(s) of a single song. The Best New Artist award is presented to a promising breakthrough performer (or performers) who in ...Read more",
            "title": "Grammy Awards",
            "url": "https://en.wikipedia.org/wiki/Grammy_Awards"
          },
          {
            "snippet": "These two artists were BEST NEW ARTIST victories from the MTV VIDEO MUSIC AWARDS and then the GRAMMY AWARDS. • 1995: HOOTIE & THE BLOWFISH - the ...Read more",
            "title": "🌟 Since its early years, the Best New Artist category at the ...",
            "url": "https://www.facebook.com/GRAMMYS/posts/-since-its-early-years-the-best-new-artist-category-at-the-grammys-has-honored-t/1327871486035186/"
          }
        ]
      }
    ],
    "sam smith gender": [
      {
        "page": 1,
        "results": [
          {
            "snippet": "",
            "title": "Sam Smith - Wikipedia",
            "url": "https://en.wikipedia.org/wiki/Sam_Smith#:~:text=In%20October%202017%2C%20Smith%20came,full%20makeup%20while%20attending%20school%22."
          },
          {
            "snippet": "Sam Smith has come out as non-binary saying he feels \"like a woman sometimes\" and has considered having a sex change.Read more",
            "title": "Sam Smith comes out as non-binary: 'I'm not male or female'",
            "url": "https://www.bbc.com/news/newsbeat-47612616"
          },
          {
            "snippet": "I've decided I am changing my pronouns to THEY/THEM ❤ after a lifetime of being at war with my gender I've decided to embrace myself for who I ...Read more",
            "title": "Sam Smith",
            "url": "https://x.com/samsmith/status/1172519872464662530"
          },
          {
            "snippet": "Singer Sam Smith has shared insights into their gender identity, saying, “I'm not male or female; I think I flow somewhere in between.",
            "title": "Singer Sam Smith has shared insights into their gender ...",
            "url": "https://www.facebook.com/adizthebam/posts/singer-sam-smith-has-shared-insights-into-their-gender-identity-saying-im-not-ma/1449415876756809/"
          },
          {
            "snippet": "Famed singer Sam Smith revealed for the first time in an interview on Friday that he identifies as gender neutral.Read more",
            "title": "Famous singer Sam Smith: I am neither male nor female!",
            "url": "https://telegrafi.com/en/the-famous-singer-sam-smith-i-am-not-a-feminine-man/"
          },
          {
            "snippet": "Smith is hardly the first celebrity to come out as gender nonbinary. But Smith is still read and understood by society to be a “man,” based ...Read more",
            "title": "Sam Smith's they/them pronoun backlash highlights ...",
            "url": "https://www.reddit.com/r/genderqueer/comments/d7fph3/sam_smiths_theythem_pronoun_backlash_highlights/"
          },
          {
            "snippet": "Smith came out as non-binary in 2019, and later made history as the first openly non-binary artist to win a Grammy Award for their Kim Petras- ...Read more",
            "title": "Sam Smith has removed the gendered pronouns in a re- ...",
            "url": "https://www.instagram.com/p/C9SSsFxMUYY/?hl=en"
          },
          {
            "snippet": "The singer said he doesn't identify as male or female. By Sarah Young Last week, Sam Smith revealed that he identifies as non-binary and genderqueer.",
            "title": "What does non-binary mean? Definition after Sam Smith ...",
            "url": "https://www.issuesonline.co.uk/articles/what-does-nonbinary-mean-definition-after-sam-smith-comes-out-as-genderqueer"
          }
        ]
      }
    ]
  },
  "click": [
    {
      "from": "https://en.wikipedia.org/wiki/Grammy_Award_for_Best_New_Artist",
      "to": "https://en.wikipedia.org/wiki/Sheryl_Crow"
    },
    {
      "from": "https://en.wikipedia.org/wiki/Grammy_Award_for_Best_New_Artist#1990s",
      "to": "https://en.wikipedia.org/wiki/Sheryl_Crow"
    },
    {
      "from": "https://en.wikipedia.org/wiki/Grammy_Award_for_Best_New_Artist#1990s",
      "to": "https://en.wikipedia.org/wiki/Hootie_%26_the_Blowfish"
    },
    {
      "from": "https://en.wikipedia.org/wiki/Grammy_Award_for_Best_New_Artist#1990s",
      "to": "https://en.wikipedia.org/wiki/LeAnn_Rimes"
    },
    {
      "from": "https://en.wikipedia.org/wiki/Grammy_Award_for_Best_New_Artist#1990s",
      "to": "https://en.wikipedia.org/wiki/Paula_Cole"
    },
    {
      "from": "https://en.wikipedia.org/wiki/Grammy_Award_for_Best_New_Artist#1990s",
      "to": "https://en.wikipedia.org/wiki/Lauryn_Hill"
    },
    {
      "from": "https://en.wikipedia.org/wiki/Grammy_Award_for_Best_New_Artist#1990s",
      "to": "https://en.wikipedia.org/wiki/Christina_Aguilera"
    },
    {
      "from": "https://en.wikipedia.org/wiki/Grammy_Award_for_Best_New_Artist#1990s",
      "to": "https://en.wikipedia.org/wiki/Shelby_Lynne"
    },
    {
      "from": "https://en.wikipedia.org/wiki/Grammy_Award_for_Best_New_Artist#1990s",
      "to": "https://en.wikipedia.org/wiki/Alicia_Keys"
    },
    {
      "from": "https://en.wikipedia.org/wiki/Grammy_Award_for_Best_New_Artist#1990s",
      "to": "https://en.wikipedia.org/wiki/Alicia_Keys"
    },
    {
      "from": "https://en.wikipedia.org/wiki/Grammy_Award_for_Best_New_Artist#1990s",
      "to": "https://en.wikipedia.org/wiki/Norah_Jones"
    },
    {
      "from": "https://en.wikipedia.org/wiki/Grammy_Award_for_Best_New_Artist#1990s",
      "to": "https://en.wikipedia.org/wiki/Evanescence"
    },
    {
      "from": "https://en.wikipedia.org/wiki/Grammy_Award_for_Best_New_Artist#1990s",
      "to": "https://en.wikipedia.org/wiki/John_Legend"
    },
    {
      "from": "https://en.wikipedia.org/wiki/Grammy_Award_for_Best_New_Artist#1990s",
      "to": "https://en.wikipedia.org/wiki/Carrie_Underwood"
    },
    {
      "from": "https://en.wikipedia.org/wiki/Grammy_Award_for_Best_New_Artist#1990s",
      "to": "https://en.wikipedia.org/wiki/Amy_Winehouse"
    },
    {
      "from": "https://en.wikipedia.org/wiki/Grammy_Award_for_Best_New_Artist#1990s",
      "to": "https://en.wikipedia.org/wiki/Adele"
    },
    {
      "from": "https://en.wikipedia.org/wiki/Grammy_Award_for_Best_New_Artist#1990s",
      "to": "https://en.wikipedia.org/wiki/Zac_Brown_Band"
    },
    {
      "from": "https://en.wikipedia.org/wiki/Grammy_Award_for_Best_New_Artist#1990s",
      "to": "https://en.wikipedia.org/wiki/Esperanza_Spalding"
    },
    {
      "from": "https://en.wikipedia.org/wiki/Grammy_Award_for_Best_New_Artist#1990s",
      "to": "https://en.wikipedia.org/wiki/Sam_Smith"
    },
    {
      "from": "https://en.wikipedia.org/wiki/Grammy_Award_for_Best_New_Artist#1990s",
      "to": "https://en.wikipedia.org/wiki/Meghan_Trainor"
    },
    {
      "from": "https://en.wikipedia.org/wiki/Grammy_Award_for_Best_New_Artist#1990s",
      "to": "https://en.wikipedia.org/wiki/Chance_the_Rapper"
    },
    {
      "from": "https://en.wikipedia.org/wiki/Grammy_Award_for_Best_New_Artist#1990s",
      "to": "https://en.wikipedia.org/wiki/Alessia_Cara"
    },
    {
      "from": "https://en.wikipedia.org/wiki/Grammy_Award_for_Best_New_Artist#1990s",
      "to": "https://en.wikipedia.org/wiki/Dua_Lipa"
    },
    {
      "from": "https://en.wikipedia.org/wiki/Grammy_Award_for_Best_New_Artist#1990s",
      "to": "https://en.wikipedia.org/wiki/Billie_Eilish"
    },
    {
      "from": "https://en.wikipedia.org/wiki/Grammy_Award_for_Best_New_Artist#1990s",
      "to": "https://en.wikipedia.org/wiki/Megan_Thee_Stallion"
    },
    {
      "from": "https://en.wikipedia.org/wiki/Grammy_Award_for_Best_New_Artist#1990s",
      "to": "https://en.wikipedia.org/wiki/Olivia_Rodrigo"
    },
    {
      "from": "https://en.wikipedia.org/wiki/Grammy_Award_for_Best_New_Artist#1990s",
      "to": "https://en.wikipedia.org/wiki/Samara_Joy"
    },
    {
      "from": "https://en.wikipedia.org/wiki/Grammy_Award_for_Best_New_Artist#1990s",
      "to": "https://en.wikipedia.org/wiki/Victoria_Mon%C3%A9t"
    },
    {
      "from": "https://en.wikipedia.org/wiki/Grammy_Award_for_Best_New_Artist#1990s",
      "to": "https://en.wikipedia.org/wiki/Chappell_Roan"
    },
    {
      "from": "https://en.wikipedia.org/wiki/Grammy_Award_for_Best_New_Artist#1990s",
      "to": "https://en.wikipedia.org/wiki/Sam_Smith"
    }
  ]
}
